{
  "default": {
    "striped-primary-dark-xx": "<span class=\"card card--striped card--background-striped-primary-dark-xx\" style=\"padding:0\">Primary Darker</span>",
    "striped-primary-dark-x": "<span class=\"card card--striped card--background-striped-primary-dark-x\">Primary Dark</span>",
    "striped-primary-light-xx": "<span class=\"card card--striped card--background-striped-primary-light-xx\">Primary Lighter</span>",
    "striped-secondary-dark-xx": "<span class=\"card card--striped card--background-striped-secondary-dark-xx\">Secondary Darker</span>",
    "striped-secondary": "<span class=\"card card--striped card--background-striped-secondary\">Secondary</span>",
    "striped-accent-warm-dark-x": "<span class=\"card card--striped card--background-striped-accent-warm-dark-x\">Accent Warm Dark</span>",
    "striped-base-dark-x": "<span class=\"card card--striped card--background-striped-base-dark-x\">Base Dark</span>"
  }
}
